smilite/__init__.py
smilite/smilite.py
smilite-2.3.0.dist-info/LICENSE.txt
smilite-2.3.0.dist-info/METADATA
smilite-2.3.0.dist-info/WHEEL
smilite-2.3.0.dist-info/top_level.txt
smilite-2.3.0.dist-info/RECORD
