Metadata-Version: 2.1
Name: smilite
Version: 2.3.0
Summary: smilite is a Python module to download and analyze SMILE strings
Home-page: https://github.com/rasbt/smilite
Author: Sebastian Raschka
Author-email: se.raschka@gmail.com
License: GPLv3
Platform: any
Classifier: License :: OSI Approved :: GNU General Public License v3 (GPLv3)
Classifier: Development Status :: 5 - Production/Stable
Classifier: Programming Language :: Python :: 3
Classifier: Environment :: Console
Requires-Dist: PyPrind (>=2.3.1)
